vizdata/__init__.py
vizdata/advanced.py
vizdata/cats.py
vizdata/eda.py
vizdata/generator.py
vizdata/heatmap.py
vizdata/nums.py
vizdata/parallel.py
vizdata/utils.py
vizdata-0.32.dist-info/LICENSE
vizdata-0.32.dist-info/METADATA
vizdata-0.32.dist-info/WHEEL
vizdata-0.32.dist-info/top_level.txt
vizdata-0.32.dist-info/RECORD
