Metadata-Version: 2.1
Name: vizdata
Version: 0.32
Summary: Simple Exploratory Data Analysis tool.
Home-page: https://github.com/darkhan-ai/vizdata
License: MIT
License-File: LICENSE
Requires-Dist: pandas
